fakemcp/__init__.py
fakemcp/actor_manager.py
fakemcp/config.py
fakemcp/data_generator.py
fakemcp/database.py
fakemcp/errors.py
fakemcp/logger.py
fakemcp/main.py
fakemcp/mcp_server.py
fakemcp/models.py
fakemcp/plot_manager.py
fakemcp/scenario_manager.py
fakemcp/target_mcp_analyzer.py
fakemcp/validation_service.py
fakemcp/workflow_guide.py
fakemcp/tools/__init__.py
fakemcp/tools/actor_tools.py
fakemcp/tools/data_tools.py
fakemcp/tools/guide_tool.py
fakemcp/tools/persistence_tools.py
fakemcp/tools/plot_tools.py
fakemcp/tools/scenario_tools.py
fakemcp-0.1.0.dist-info/METADATA
fakemcp-0.1.0.dist-info/WHEEL
fakemcp-0.1.0.dist-info/entry_points.txt
fakemcp-0.1.0.dist-info/top_level.txt
fakemcp-0.1.0.dist-info/RECORD
