Metadata-Version: 2.4
Name: fakemcp
Version: 0.1.0
Summary: Intelligent MCP server simulator for testing AI agents with scenario-driven mock data generation
Author-email: FakeMCP Team <fakemcp@example.com>
Maintainer-email: FakeMCP Team <fakemcp@example.com>
License-Expression: MIT
Project-URL: Homepage, https://github.com/yourusername/fakemcp
Project-URL: Documentation, https://github.com/yourusername/fakemcp#readme
Project-URL: Repository, https://github.com/yourusername/fakemcp
Project-URL: Issues, https://github.com/yourusername/fakemcp/issues
Keywords: mcp,testing,mock,simulator,ai-agent
Classifier: Development Status :: 4 - Beta
Classifier: Intended Audience :: Developers
Classifier: Programming Language :: Python :: 3
Classifier: Programming Language :: Python :: 3.10
Classifier: Programming Language :: Python :: 3.11
Classifier: Programming Language :: Python :: 3.12
Classifier: Programming Language :: Python :: 3.13
Classifier: Topic :: Software Development :: Testing
Classifier: Topic :: Software Development :: Testing :: Mocking
Requires-Python: >=3.10
Requires-Dist: mcp>=0.1.0
Requires-Dist: httpx>=0.24.0
Requires-Dist: jsonschema>=4.17.0
Requires-Dist: pyyaml>=6.0
Provides-Extra: dev
Requires-Dist: pytest>=7.0.0; extra == "dev"
Requires-Dist: pytest-asyncio>=0.21.0; extra == "dev"
Requires-Dist: pytest-cov>=4.0.0; extra == "dev"
